orchestra_cli/src/__init__.py
orchestra_cli/src/cli.py
orchestra_cli/src/import_pipeline.py
orchestra_cli/src/run_pipeline.py
orchestra_cli/src/validate_pipeline.py
orchestra_cli/tests/__init__.py
orchestra_cli/tests/conftest.py
orchestra_cli/tests/test_cli.py
orchestra_cli/tests/test_import_pipeline.py
orchestra_cli/tests/test_run_pipeline.py
orchestra_cli/tests/test_validate_pipeline.py
orchestra_cli/utils/constants.py
orchestra_cli/utils/git.py
orchestra_cli/utils/styling.py
orchestra_cli-0.1.1.dist-info/METADATA
orchestra_cli-0.1.1.dist-info/WHEEL
orchestra_cli-0.1.1.dist-info/entry_points.txt
orchestra_cli-0.1.1.dist-info/top_level.txt
orchestra_cli-0.1.1.dist-info/RECORD
