Metadata-Version: 2.4
Name: orchestra-cli
Version: 0.1.1
Summary: Orchestra CLI. Perform operations with Orchestra locally.
Author-email: Orchestra Technologies <support@getorchestra.io>
Requires-Python: >=3.10
Requires-Dist: httpx>=0.28.1
Requires-Dist: pyyaml>=6.0.2
Requires-Dist: typer>=0.16.0
